quick_pypi_test/__init__.py
quick_pypi_test/lib.ipynb
quick_pypi_test-0.0.4.dist-info/LICENSE
quick_pypi_test-0.0.4.dist-info/METADATA
quick_pypi_test-0.0.4.dist-info/WHEEL
quick_pypi_test-0.0.4.dist-info/entry_points.txt
quick_pypi_test-0.0.4.dist-info/top_level.txt
quick_pypi_test-0.0.4.dist-info/RECORD
